dummy_notebookutils-1.6.3.dist-info/licenses/LICENSE
notebookutils/__init__.py
notebookutils/conf.py
notebookutils/connections.py
notebookutils/credentials.py
notebookutils/data.py
notebookutils/fabricClient.py
notebookutils/fs.py
notebookutils/lakehouse.py
notebookutils/notebook.py
notebookutils/runtime.py
notebookutils/session.py
notebookutils/udf.py
notebookutils/variableLibrary.py
notebookutils/mssparkutils/__init__.py
notebookutils/mssparkutils/credentials.py
notebookutils/mssparkutils/env.py
notebookutils/mssparkutils/fs.py
notebookutils/mssparkutils/lakehouse.py
notebookutils/mssparkutils/notebook.py
notebookutils/mssparkutils/runtime.py
notebookutils/mssparkutils/session.py
dummy_notebookutils-1.6.3.dist-info/METADATA
dummy_notebookutils-1.6.3.dist-info/WHEEL
dummy_notebookutils-1.6.3.dist-info/top_level.txt
dummy_notebookutils-1.6.3.dist-info/RECORD
