Metadata-Version: 2.4
Name: dummy-notebookutils
Version: 1.6.3
Summary: A package that allows to use synapse mssparkutils without actual functionality. This helps to generate the build.
Home-page: https://github.com/Azure/azure-synapse-analytics
Author: Microsoft Corporation
Author-email: runtimeexpdg@microsoft.com
License: MIT License
Classifier: Development Status :: 3 - Alpha
Classifier: Natural Language :: English
Classifier: Programming Language :: Python :: 3.10
Classifier: Programming Language :: Python :: 3.11
Classifier: Programming Language :: Python :: 3.12
License-File: LICENSE
Dynamic: author
Dynamic: author-email
Dynamic: classifier
Dynamic: description
Dynamic: description-content-type
Dynamic: home-page
Dynamic: license
Dynamic: license-file
Dynamic: summary
